[
  {
    "zona": "produccion",
    "artefacto": "amasadora sobadora 8lt 220v 450w",
    "potencia_kw": 0.45,
    "tension_v": 220.0,
    "fase": 1.0,
    "marca": "Grondoy",
    "precio_pen": 1890.0,
    "horas_dia": 8.0,
    "nombre_archivo": "amasadora_sobadora_8lt_220v450w.webp",
    "categoria": "panaderia"
  },
  {
    "zona": "produccion",
    "artefacto": "amasadora sobadora industrial 20lt 220v 1500w",
    "potencia_kw": 1.5,
    "tension_v": 220.0,
    "fase": 1.0,
    "marca": "Grondoy",
    "precio_pen": 3490.0,
    "horas_dia": 8.0,
    "nombre_archivo": "amasadora_sobadora_20lt_220v1500w.webp",
    "categoria": "panaderia"
  },
  {
    "zona": "produccion",
    "artefacto": "amasadora sobadora industrial 48lt 220v 3000w",
    "potencia_kw": 3.0,
    "tension_v": 220.0,
    "fase": 3.0,
    "marca": "Grondoy",
    "precio_pen": 4790.0,
    "horas_dia": 8.0,
    "nombre_archivo": "amasadora_sobadora_48lt_220v3000w.webp",
    "categoria": "panaderia"
  },
  {
    "zona": "produccion",
    "artefacto": "amasadora sobadora industrial 60lt 220v 4000w",
    "potencia_kw": 4.0,
    "tension_v": 220.0,
    "fase": 3.0,
    "marca": "Grondoy",
    "precio_pen": 5690.0,
    "horas_dia": 8.0,
    "nombre_archivo": "amasadora_sobadora_60lt_220v4000w.webp",
    "categoria": "panaderia"
  },
  {
    "zona": "produccion",
    "artefacto": "batidora planetaria para masas y tortas 220v 350w",
    "potencia_kw": 0.35,
    "tension_v": 220.0,
    "fase": 1.0,
    "marca": "Grondoy",
    "precio_pen": 1290.0,
    "horas_dia": 8.0,
    "nombre_archivo": "batidora_planetaria_220v350w.webp",
    "categoria": "panaderia"
  },
  {
    "zona": "produccion",
    "artefacto": "batidora tortas 7lt 350w",
    "potencia_kw": 0.35,
    "tension_v": 220.0,
    "fase": 1.0,
    "marca": "Grondoy",
    "precio_pen": 1290.0,
    "horas_dia": 5.0,
    "nombre_archivo": "batidora_tortas_7lt_220v350w.webp",
    "categoria": "panaderia"
  },
  {
    "zona": "produccion",
    "artefacto": "batidora amasadora 30lt 1.5hp",
    "potencia_kw": 1.119,
    "tension_v": 220.0,
    "fase": 1.0,
    "marca": "Grondoy",
    "precio_pen": 2790.0,
    "horas_dia": 5.0,
    "nombre_archivo": "batidora_amasadora_30lt_220v1119w.webp",
    "categoria": "panaderia"
  },
  {
    "zona": "produccion",
    "artefacto": "balanza gramera 15000gr tscale",
    "potencia_kw": 0.005,
    "tension_v": 220.0,
    "fase": 1.0,
    "marca": "T-Scale",
    "precio_pen": 890.0,
    "horas_dia": 5.0,
    "nombre_archivo": "balanza_gramera_220v5w.webp",
    "categoria": "panaderia"
  },
  {
    "zona": "produccion",
    "artefacto": "balanza digital de plataforma lisa 220v 5w",
    "potencia_kw": 0.005,
    "tension_v": 220.0,
    "fase": 1.0,
    "marca": "Exeltor",
    "precio_pen": 350.0,
    "horas_dia": 5.0,
    "nombre_archivo": "balanza_digital_plataforma_220v5w.webp",
    "categoria": "panaderia"
  },
  {
    "zona": "produccion",
    "artefacto": "divisora boleadora 220v 1300w",
    "potencia_kw": 1.3,
    "tension_v": 220.0,
    "fase": 3.0,
    "marca": "Daub",
    "precio_pen": 7000.0,
    "horas_dia": 5.0,
    "nombre_archivo": "divisora_boleadora_220v1300w.webp",
    "categoria": "panaderia"
  },
  {
    "zona": "produccion",
    "artefacto": "Laminadora de masa Industrial 220v 3hp",
    "potencia_kw": 2.238,
    "tension_v": 220.0,
    "fase": 3.0,
    "marca": "Dakota",
    "precio_pen": 2790.0,
    "horas_dia": 5.0,
    "nombre_archivo": "laminadora_masa_industrial_220v3hp.webp",
    "categoria": "panaderia"
  },
  {
    "zona": "produccion",
    "artefacto": "camara fermentacion max750 1coche 220v 850w",
    "potencia_kw": 0.85,
    "tension_v": 220.0,
    "fase": 1.0,
    "marca": "Nova",
    "precio_pen": 4980.0,
    "horas_dia": 5.0,
    "nombre_archivo": "camara_fermentacion_220v850w.webp",
    "categoria": "panaderia"
  },
  {
    "zona": "produccion",
    "artefacto": "Hormo pizzero 1.5kw",
    "potencia_kw": 1.5,
    "tension_v": 220.0,
    "fase": 1.0,
    "marca": "Ventus",
    "precio_pen": 1200.0,
    "horas_dia": 5.0,
    "nombre_archivo": "horno_pizzero_220v1500w.webp",
    "categoria": "panaderia"
  },
  {
    "zona": "produccion",
    "artefacto": "horno electrico 4 band 288panh",
    "potencia_kw": 1.87,
    "tension_v": 220.0,
    "fase": 1.0,
    "marca": "Indhor",
    "precio_pen": 5000.0,
    "horas_dia": 5.0,
    "nombre_archivo": "horno_electrico_220v1870w.webp",
    "categoria": "panaderia"
  },
  {
    "zona": "produccion",
    "artefacto": "horno conv electrico 6 band 720panh",
    "potencia_kw": 5.8,
    "tension_v": 380.0,
    "fase": 3.0,
    "marca": "Indhor",
    "precio_pen": 5000.0,
    "horas_dia": 5.0,
    "nombre_archivo": "horno_conv_electrico_380v5800w.webp",
    "categoria": "panaderia"
  },
  {
    "zona": "produccion",
    "artefacto": "horno mixto profesional de sobremesa",
    "potencia_kw": 14.3,
    "tension_v": 380.0,
    "fase": 3.0,
    "marca": "Unox",
    "precio_pen": 8000.0,
    "horas_dia": 8.0,
    "nombre_archivo": "horno_mixto_sobremesa_380v14300w.webp",
    "categoria": "panaderia"
  },
  {
    "zona": "produccion",
    "artefacto": "horno rotativo 12 bandejas 1152 panes/hora 220v 2hp",
    "potencia_kw": 1.49,
    "tension_v": 220.0,
    "fase": 1.0,
    "marca": "Indhor",
    "precio_pen": 25000.0,
    "horas_dia": 8.0,
    "nombre_archivo": "horno_rotativo_12band_1152panes_220v2hp.webp",
    "categoria": "panaderia"
  },
  {
    "zona": "produccion",
    "artefacto": "horno convector gas carro trolley 12band",
    "potencia_kw": 1.8,
    "tension_v": 220.0,
    "fase": 1.0,
    "marca": "Ilumi",
    "precio_pen": 28590.0,
    "horas_dia": 8.0,
    "nombre_archivo": "horno_conv_gas_12band_220v1800w.webp",
    "categoria": "panaderia"
  },
  {
    "zona": "produccion",
    "artefacto": "rebanadora de pan 37 cortes",
    "potencia_kw": 0.373,
    "tension_v": 220.0,
    "fase": 1.0,
    "marca": "Maqorito",
    "precio_pen": 3700.0,
    "horas_dia": 5.0,
    "nombre_archivo": "rebanadora_pan_220v373w.webp",
    "categoria": "panaderia"
  },
  {
    "zona": "produccion",
    "artefacto": "rebanadora one 37cortes",
    "potencia_kw": 0.75,
    "tension_v": 220.0,
    "fase": 3.0,
    "marca": "Nova",
    "precio_pen": 4000.0,
    "horas_dia": 5.0,
    "nombre_archivo": "rebanadora_pan_220v750w.webp",
    "categoria": "panaderia"
  },
  {
    "zona": "refrigeracion",
    "artefacto": "vitr refrig vidrio plano 550w",
    "potencia_kw": 0.55,
    "tension_v": 220.0,
    "fase": 1.0,
    "marca": "Ilumi",
    "precio_pen": 8599.0,
    "horas_dia": 8.0,
    "nombre_archivo": "vitrina_refrigeradora_220v550w.webp",
    "categoria": "panaderia"
  }
]